deidentify/__init__.py
deidentify/base.py
deidentify/dataset/__init__.py
deidentify/dataset/brat.py
deidentify/dataset/brat2corpus.py
deidentify/dataset/corpus_loader.py
deidentify/dataset/nursing2brat.py
deidentify/dataset/uthealth2corpus.py
deidentify/evaluation/__init__.py
deidentify/evaluation/art.py
deidentify/evaluation/evaluate_corpus.py
deidentify/evaluation/evaluate_run.py
deidentify/evaluation/evaluator.py
deidentify/evaluation/iaa.py
deidentify/evaluation/metric.py
deidentify/evaluation/significance_testing.py
deidentify/methods/__init__.py
deidentify/methods/tagging_utils.py
deidentify/methods/train_utils.py
deidentify/methods/bilstmcrf/__init__.py
deidentify/methods/bilstmcrf/flair_utils.py
deidentify/methods/bilstmcrf/run_bilstmcrf.py
deidentify/methods/bilstmcrf/run_bilstmcrf_training_sample.py
deidentify/methods/crf/__init__.py
deidentify/methods/crf/crf_labeler.py
deidentify/methods/crf/crf_util.py
deidentify/methods/crf/run_crf.py
deidentify/methods/crf/run_crf_hyperopt.py
deidentify/methods/crf/run_crf_learning_curve.py
deidentify/methods/crf/run_crf_training_sample.py
deidentify/methods/deduce/__init__.py
deidentify/methods/deduce/deduce_labeler.py
deidentify/methods/deduce/patch_deduce_institute_list.py
deidentify/methods/deduce/run_deduce.py
deidentify/methods/deduce/unflatten_deduce_predictions.py
deidentify/surrogates/__init__.py
deidentify/surrogates/dataset_deidentifier.py
deidentify/surrogates/generate_surrogates.py
deidentify/surrogates/rewrite_dataset.py
deidentify/surrogates/generators/__init__.py
deidentify/surrogates/generators/age.py
deidentify/surrogates/generators/base.py
deidentify/surrogates/generators/corpus_shuffle.py
deidentify/surrogates/generators/date.py
deidentify/surrogates/generators/email.py
deidentify/surrogates/generators/identifier.py
deidentify/surrogates/generators/location.py
deidentify/surrogates/generators/name.py
deidentify/surrogates/generators/phone.py
deidentify/surrogates/generators/url.py
deidentify-0.7.3.dist-info/LICENSE
deidentify-0.7.3.dist-info/METADATA
deidentify-0.7.3.dist-info/WHEEL
deidentify-0.7.3.dist-info/top_level.txt
deidentify-0.7.3.dist-info/RECORD
