Metadata-Version: 2.1
Name: deidentify
Version: 0.7.3
Summary: De-identify free-text medical records
Home-page: https://github.com/nedap/deidentify
Author: Jan Trienes
Author-email: jan.trienes@nedap.com
License: MIT License
Platform: UNKNOWN
Classifier: Programming Language :: Python :: 3
Classifier: Programming Language :: Python :: 3.6
Classifier: Programming Language :: Python :: 3.7
Classifier: Programming Language :: Python :: 3.8
Classifier: Programming Language :: Python :: 3.9
Classifier: Operating System :: OS Independent
Classifier: License :: OSI Approved :: MIT License
Requires-Python: >=3.7
License-File: LICENSE
Requires-Dist: requests
Requires-Dist: flair (<0.11,>=0.4.3)
Requires-Dist: torch (>=1.1.0)
Requires-Dist: spacy (<3,>=2.2.1)
Requires-Dist: tqdm (>=4.29)
Requires-Dist: deduce (>=1.0.2)
Requires-Dist: loguru (>=0.2.5)
Requires-Dist: sklearn-crfsuite (>=0.3.6)
Requires-Dist: unidecode (>=1.0.23)
Requires-Dist: pandas (>=0.23.4)
Requires-Dist: nameparser (>=1.0)
Requires-Dist: py-dateinfer (>=0.4.5)
